CHANGES
LICENSE
MANIFEST.in
README.rst
cachual.py
setup.cfg
setup.py
Cachual.egg-info/PKG-INFO
Cachual.egg-info/SOURCES.txt
Cachual.egg-info/dependency_links.txt
Cachual.egg-info/not-zip-safe
Cachual.egg-info/requires.txt
Cachual.egg-info/top_level.txt
docs/.gitignore
docs/Makefile
docs/conf.py
docs/dump.rdb
docs/index.rst
tests/test_cachual.py
tests/test_end_to_end.py
tests/test_key.py
tests/test_memcached_cache.py
tests/test_packing_functions.py
tests/test_redis_cache.py