Metadata-Version: 1.1
Name: Cachual
Version: 0.2.2
Summary: Simple annotation-based caching for your functions
Home-page: https://github.com/bal2ag/cachual
Author: Alex Landau
Author-email: balexlandau@gmail.com
License: BSD
Platform: any
Classifier: Development Status :: 4 - Beta
Classifier: Intended Audience :: Developers
Classifier: Operating System :: OS Independent
Classifier: Programming Language :: Python
Classifier: Programming Language :: Python :: 2
Classifier: Programming Language :: Python :: 3
Classifier: Topic :: Software Development :: Libraries :: Python Modules
